LICENSE
MANIFEST.in
README.md
requirements.txt
setup.cfg
setup.py
django_mp_warehouses.egg-info/PKG-INFO
django_mp_warehouses.egg-info/SOURCES.txt
django_mp_warehouses.egg-info/dependency_links.txt
django_mp_warehouses.egg-info/top_level.txt
warehouses/__init__.py
warehouses/admin.py
warehouses/models.py
warehouses/locale/ru/LC_MESSAGES/django.mo
warehouses/locale/ru/LC_MESSAGES/django.po
warehouses/locale/uk/LC_MESSAGES/django.mo
warehouses/locale/uk/LC_MESSAGES/django.po
warehouses/migrations/0001_initial.py
warehouses/migrations/__init__.py