Metadata-Version: 1.1
Name: django-mp-warehouses
Version: 0.1
Summary: Django warehouses app
Home-page: https://github.com/pmaigutyak/mp-warehouses
Author: Paul Maigutyak
Author-email: pmaigutyak@gmail.com
License: MIT
Download-URL: https://github.com/pmaigutyak/mp-warehouses/archive/0.1.tar.gz
Platform: UNKNOWN
